web_playground/__init__.py
web_playground/app.py
web_playground/run.py
web_playground/static/css/common.css
web_playground/static/css/external/bootstrap.min.css
web_playground/static/images/airplane.png
web_playground/static/images/cat-image.jpg
web_playground/static/js/common.js
web_playground/static/js/external/bootstrap.min.js
web_playground/static/js/external/jquery.min.js
web_playground/templates/ajax_request.html
web_playground/templates/all_disabled_elements.html
web_playground/templates/base.html
web_playground/templates/component_library.html
web_playground/templates/disabled_elements.html
web_playground/templates/drag_and_drop.html
web_playground/templates/dynamic_elements.html
web_playground/templates/elements.html
web_playground/templates/form_basic.html
web_playground/templates/form_basic_result.html
web_playground/templates/index.html
web_playground/templates/special_elements.html
web_playground/templates/tab.html
web_playground/templates/table-basic.html
web_playground/templates/tabs.html
web_playground/templates/alerts/alert.html
web_playground/templates/alerts/confirm.html
web_playground/templates/alerts/confirm_exit.html
web_playground/templates/alerts/prompt.html
web_playground/templates/frames/frame_bottom.html
web_playground/templates/frames/frame_bottom_left.html
web_playground/templates/frames/frame_bottom_right.html
web_playground/templates/frames/frame_top.html
web_playground/templates/frames/frames.html
web_playground/templates/frames/iframe_bottom.html
web_playground/templates/frames/iframe_bottom_left.html
web_playground/templates/frames/iframe_bottom_right.html
web_playground/templates/frames/iframe_top.html
web_playground/templates/frames/iframes.html
web_playground-0.0.1.dist-info/LICENSE
web_playground-0.0.1.dist-info/METADATA
web_playground-0.0.1.dist-info/WHEEL
web_playground-0.0.1.dist-info/entry_points.txt
web_playground-0.0.1.dist-info/top_level.txt
web_playground-0.0.1.dist-info/RECORD
