Metadata-Version: 2.1
Name: web-playground
Version: 0.0.1
Summary: Demo web application for testing purposes
Home-page: http://github.com/golemhq/web-playground
Author: Luciano Renzi
Author-email: luciano@lucianorenzi.com
License: UNKNOWN
Keywords: test automation selenium webdriver web web-playground
Platform: UNKNOWN
Classifier: Topic :: Internet :: WWW/HTTP :: Browsers
Classifier: Topic :: Software Development :: Testing
Requires-Dist: flask
